<?xml version="1.0" encoding="UTF-8" ?>
<!DOCTYPE mapper PUBLIC "-//mybatis.org//DTD Mapper 3.0//EN" "http://mybatis.org/dtd/mybatis-3-mapper.dtd" >
<mapper namespace="com.example.demo.dal.WaysBuilderMapper" >
  <resultMap id="BaseResultMap" type="com.example.demo.model.WaysBuilder" >
    <!--
      WARNING - @mbggenerated
      This element is automatically generated by MyBatis Generator, do not modify.
      This element was generated on Tue Apr 14 15:47:07 CST 2020.
    -->
    <id column="builder_id" property="builderId" jdbcType="INTEGER" />
    <result column="builder_name" property="builderName" jdbcType="VARCHAR" />
    <result column="mobile" property="mobile" jdbcType="VARCHAR" />
    <result column="constuction_id" property="constuctionId" jdbcType="INTEGER" />
    <result column="build_type" property="buildType" jdbcType="INTEGER" />
    <result column="identity_type" property="identityType" jdbcType="INTEGER" />
    <result column="identity_code" property="identityCode" jdbcType="VARCHAR" />
    <result column="id_start_time" property="idStartTime" jdbcType="INTEGER" />
    <result column="id_end_time" property="idEndTime" jdbcType="INTEGER" />
    <result column="id_images" property="idImages" jdbcType="INTEGER" />
    <result column="is_principal" property="isPrincipal" jdbcType="SMALLINT" />
    <result column="is_join" property="isJoin" jdbcType="SMALLINT" />
    <result column="decoration_id" property="decorationId" jdbcType="INTEGER" />
    <result column="create_by" property="createBy" jdbcType="INTEGER" />
    <result column="create_time" property="createTime" jdbcType="INTEGER" />
    <result column="update_time" property="updateTime" jdbcType="INTEGER" />
  </resultMap>
  <sql id="Example_Where_Clause" >
    <!--
      WARNING - @mbggenerated
      This element is automatically generated by MyBatis Generator, do not modify.
      This element was generated on Tue Apr 14 15:47:07 CST 2020.
    -->
    <where >
      <foreach collection="oredCriteria" item="criteria" separator="or" >
        <if test="criteria.valid" >
          <trim prefix="(" suffix=")" prefixOverrides="and" >
            <foreach collection="criteria.criteria" item="criterion" >
              <choose >
                <when test="criterion.noValue" >
                  and ${criterion.condition}
                </when>
                <when test="criterion.singleValue" >
                  and ${criterion.condition} #{criterion.value}
                </when>
                <when test="criterion.betweenValue" >
                  and ${criterion.condition} #{criterion.value} and #{criterion.secondValue}
                </when>
                <when test="criterion.listValue" >
                  and ${criterion.condition}
                  <foreach collection="criterion.value" item="listItem" open="(" close=")" separator="," >
                    #{listItem}
                  </foreach>
                </when>
              </choose>
            </foreach>
          </trim>
        </if>
      </foreach>
    </where>
  </sql>
  <sql id="Update_By_Example_Where_Clause" >
    <!--
      WARNING - @mbggenerated
      This element is automatically generated by MyBatis Generator, do not modify.
      This element was generated on Tue Apr 14 15:47:07 CST 2020.
    -->
    <where >
      <foreach collection="example.oredCriteria" item="criteria" separator="or" >
        <if test="criteria.valid" >
          <trim prefix="(" suffix=")" prefixOverrides="and" >
            <foreach collection="criteria.criteria" item="criterion" >
              <choose >
                <when test="criterion.noValue" >
                  and ${criterion.condition}
                </when>
                <when test="criterion.singleValue" >
                  and ${criterion.condition} #{criterion.value}
                </when>
                <when test="criterion.betweenValue" >
                  and ${criterion.condition} #{criterion.value} and #{criterion.secondValue}
                </when>
                <when test="criterion.listValue" >
                  and ${criterion.condition}
                  <foreach collection="criterion.value" item="listItem" open="(" close=")" separator="," >
                    #{listItem}
                  </foreach>
                </when>
              </choose>
            </foreach>
          </trim>
        </if>
      </foreach>
    </where>
  </sql>
  <sql id="Base_Column_List" >
    <!--
      WARNING - @mbggenerated
      This element is automatically generated by MyBatis Generator, do not modify.
      This element was generated on Tue Apr 14 15:47:07 CST 2020.
    -->
    builder_id, builder_name, mobile, constuction_id, build_type, identity_type, identity_code, 
    id_start_time, id_end_time, id_images, is_principal, is_join, decoration_id, create_by, 
    create_time, update_time
  </sql>
  <select id="selectByExample" resultMap="BaseResultMap" parameterType="com.example.demo.model.WaysBuilderExample" >
    <!--
      WARNING - @mbggenerated
      This element is automatically generated by MyBatis Generator, do not modify.
      This element was generated on Tue Apr 14 15:47:07 CST 2020.
    -->
    select
    <if test="distinct" >
      distinct
    </if>
    <include refid="Base_Column_List" />
    from ways_builder
    <if test="_parameter != null" >
      <include refid="Example_Where_Clause" />
    </if>
    <if test="orderByClause != null" >
      order by ${orderByClause}
    </if>
  </select>
  <select id="selectByPrimaryKey" resultMap="BaseResultMap" parameterType="java.lang.Integer" >
    <!--
      WARNING - @mbggenerated
      This element is automatically generated by MyBatis Generator, do not modify.
      This element was generated on Tue Apr 14 15:47:07 CST 2020.
    -->
    select 
    <include refid="Base_Column_List" />
    from ways_builder
    where builder_id = #{builderId,jdbcType=INTEGER}
  </select>
  <delete id="deleteByPrimaryKey" parameterType="java.lang.Integer" >
    <!--
      WARNING - @mbggenerated
      This element is automatically generated by MyBatis Generator, do not modify.
      This element was generated on Tue Apr 14 15:47:07 CST 2020.
    -->
    delete from ways_builder
    where builder_id = #{builderId,jdbcType=INTEGER}
  </delete>
  <delete id="deleteByExample" parameterType="com.example.demo.model.WaysBuilderExample" >
    <!--
      WARNING - @mbggenerated
      This element is automatically generated by MyBatis Generator, do not modify.
      This element was generated on Tue Apr 14 15:47:07 CST 2020.
    -->
    delete from ways_builder
    <if test="_parameter != null" >
      <include refid="Example_Where_Clause" />
    </if>
  </delete>
  <insert id="insert" parameterType="com.example.demo.model.WaysBuilder" useGeneratedKeys="true" keyProperty="builderId" >
    <!--
      WARNING - @mbggenerated
      This element is automatically generated by MyBatis Generator, do not modify.
      This element was generated on Tue Apr 14 15:47:07 CST 2020.
    -->
    insert into ways_builder (builder_name, mobile, constuction_id, 
      build_type, identity_type, identity_code, 
      id_start_time, id_end_time, id_images, 
      is_principal, is_join, decoration_id, 
      create_by, create_time, update_time
      )
    values (#{builderName,jdbcType=VARCHAR}, #{mobile,jdbcType=VARCHAR}, #{constuctionId,jdbcType=INTEGER}, 
      #{buildType,jdbcType=INTEGER}, #{identityType,jdbcType=INTEGER}, #{identityCode,jdbcType=VARCHAR}, 
      #{idStartTime,jdbcType=INTEGER}, #{idEndTime,jdbcType=INTEGER}, #{idImages,jdbcType=INTEGER}, 
      #{isPrincipal,jdbcType=SMALLINT}, #{isJoin,jdbcType=SMALLINT}, #{decorationId,jdbcType=INTEGER}, 
      #{createBy,jdbcType=INTEGER}, #{createTime,jdbcType=INTEGER}, #{updateTime,jdbcType=INTEGER}
      )
  </insert>
  <insert id="insertSelective" parameterType="com.example.demo.model.WaysBuilder" useGeneratedKeys="true" keyProperty="builderId" >
    <!--
      WARNING - @mbggenerated
      This element is automatically generated by MyBatis Generator, do not modify.
      This element was generated on Tue Apr 14 15:47:07 CST 2020.
    -->
    insert into ways_builder
    <trim prefix="(" suffix=")" suffixOverrides="," >
      <if test="builderName != null" >
        builder_name,
      </if>
      <if test="mobile != null" >
        mobile,
      </if>
      <if test="constuctionId != null" >
        constuction_id,
      </if>
      <if test="buildType != null" >
        build_type,
      </if>
      <if test="identityType != null" >
        identity_type,
      </if>
      <if test="identityCode != null" >
        identity_code,
      </if>
      <if test="idStartTime != null" >
        id_start_time,
      </if>
      <if test="idEndTime != null" >
        id_end_time,
      </if>
      <if test="idImages != null" >
        id_images,
      </if>
      <if test="isPrincipal != null" >
        is_principal,
      </if>
      <if test="isJoin != null" >
        is_join,
      </if>
      <if test="decorationId != null" >
        decoration_id,
      </if>
      <if test="createBy != null" >
        create_by,
      </if>
      <if test="createTime != null" >
        create_time,
      </if>
      <if test="updateTime != null" >
        update_time,
      </if>
    </trim>
    <trim prefix="values (" suffix=")" suffixOverrides="," >
      <if test="builderName != null" >
        #{builderName,jdbcType=VARCHAR},
      </if>
      <if test="mobile != null" >
        #{mobile,jdbcType=VARCHAR},
      </if>
      <if test="constuctionId != null" >
        #{constuctionId,jdbcType=INTEGER},
      </if>
      <if test="buildType != null" >
        #{buildType,jdbcType=INTEGER},
      </if>
      <if test="identityType != null" >
        #{identityType,jdbcType=INTEGER},
      </if>
      <if test="identityCode != null" >
        #{identityCode,jdbcType=VARCHAR},
      </if>
      <if test="idStartTime != null" >
        #{idStartTime,jdbcType=INTEGER},
      </if>
      <if test="idEndTime != null" >
        #{idEndTime,jdbcType=INTEGER},
      </if>
      <if test="idImages != null" >
        #{idImages,jdbcType=INTEGER},
      </if>
      <if test="isPrincipal != null" >
        #{isPrincipal,jdbcType=SMALLINT},
      </if>
      <if test="isJoin != null" >
        #{isJoin,jdbcType=SMALLINT},
      </if>
      <if test="decorationId != null" >
        #{decorationId,jdbcType=INTEGER},
      </if>
      <if test="createBy != null" >
        #{createBy,jdbcType=INTEGER},
      </if>
      <if test="createTime != null" >
        #{createTime,jdbcType=INTEGER},
      </if>
      <if test="updateTime != null" >
        #{updateTime,jdbcType=INTEGER},
      </if>
    </trim>
  </insert>
  <select id="countByExample" parameterType="com.example.demo.model.WaysBuilderExample" resultType="java.lang.Integer" >
    <!--
      WARNING - @mbggenerated
      This element is automatically generated by MyBatis Generator, do not modify.
      This element was generated on Tue Apr 14 15:47:07 CST 2020.
    -->
    select count(*) from ways_builder
    <if test="_parameter != null" >
      <include refid="Example_Where_Clause" />
    </if>
  </select>
  <update id="updateByExampleSelective" parameterType="map" >
    <!--
      WARNING - @mbggenerated
      This element is automatically generated by MyBatis Generator, do not modify.
      This element was generated on Tue Apr 14 15:47:07 CST 2020.
    -->
    update ways_builder
    <set >
      <if test="record.builderId != null" >
        builder_id = #{record.builderId,jdbcType=INTEGER},
      </if>
      <if test="record.builderName != null" >
        builder_name = #{record.builderName,jdbcType=VARCHAR},
      </if>
      <if test="record.mobile != null" >
        mobile = #{record.mobile,jdbcType=VARCHAR},
      </if>
      <if test="record.constuctionId != null" >
        constuction_id = #{record.constuctionId,jdbcType=INTEGER},
      </if>
      <if test="record.buildType != null" >
        build_type = #{record.buildType,jdbcType=INTEGER},
      </if>
      <if test="record.identityType != null" >
        identity_type = #{record.identityType,jdbcType=INTEGER},
      </if>
      <if test="record.identityCode != null" >
        identity_code = #{record.identityCode,jdbcType=VARCHAR},
      </if>
      <if test="record.idStartTime != null" >
        id_start_time = #{record.idStartTime,jdbcType=INTEGER},
      </if>
      <if test="record.idEndTime != null" >
        id_end_time = #{record.idEndTime,jdbcType=INTEGER},
      </if>
      <if test="record.idImages != null" >
        id_images = #{record.idImages,jdbcType=INTEGER},
      </if>
      <if test="record.isPrincipal != null" >
        is_principal = #{record.isPrincipal,jdbcType=SMALLINT},
      </if>
      <if test="record.isJoin != null" >
        is_join = #{record.isJoin,jdbcType=SMALLINT},
      </if>
      <if test="record.decorationId != null" >
        decoration_id = #{record.decorationId,jdbcType=INTEGER},
      </if>
      <if test="record.createBy != null" >
        create_by = #{record.createBy,jdbcType=INTEGER},
      </if>
      <if test="record.createTime != null" >
        create_time = #{record.createTime,jdbcType=INTEGER},
      </if>
      <if test="record.updateTime != null" >
        update_time = #{record.updateTime,jdbcType=INTEGER},
      </if>
    </set>
    <if test="_parameter != null" >
      <include refid="Update_By_Example_Where_Clause" />
    </if>
  </update>
  <update id="updateByExample" parameterType="map" >
    <!--
      WARNING - @mbggenerated
      This element is automatically generated by MyBatis Generator, do not modify.
      This element was generated on Tue Apr 14 15:47:07 CST 2020.
    -->
    update ways_builder
    set builder_id = #{record.builderId,jdbcType=INTEGER},
      builder_name = #{record.builderName,jdbcType=VARCHAR},
      mobile = #{record.mobile,jdbcType=VARCHAR},
      constuction_id = #{record.constuctionId,jdbcType=INTEGER},
      build_type = #{record.buildType,jdbcType=INTEGER},
      identity_type = #{record.identityType,jdbcType=INTEGER},
      identity_code = #{record.identityCode,jdbcType=VARCHAR},
      id_start_time = #{record.idStartTime,jdbcType=INTEGER},
      id_end_time = #{record.idEndTime,jdbcType=INTEGER},
      id_images = #{record.idImages,jdbcType=INTEGER},
      is_principal = #{record.isPrincipal,jdbcType=SMALLINT},
      is_join = #{record.isJoin,jdbcType=SMALLINT},
      decoration_id = #{record.decorationId,jdbcType=INTEGER},
      create_by = #{record.createBy,jdbcType=INTEGER},
      create_time = #{record.createTime,jdbcType=INTEGER},
      update_time = #{record.updateTime,jdbcType=INTEGER}
    <if test="_parameter != null" >
      <include refid="Update_By_Example_Where_Clause" />
    </if>
  </update>
  <update id="updateByPrimaryKeySelective" parameterType="com.example.demo.model.WaysBuilder" >
    <!--
      WARNING - @mbggenerated
      This element is automatically generated by MyBatis Generator, do not modify.
      This element was generated on Tue Apr 14 15:47:07 CST 2020.
    -->
    update ways_builder
    <set >
      <if test="builderName != null" >
        builder_name = #{builderName,jdbcType=VARCHAR},
      </if>
      <if test="mobile != null" >
        mobile = #{mobile,jdbcType=VARCHAR},
      </if>
      <if test="constuctionId != null" >
        constuction_id = #{constuctionId,jdbcType=INTEGER},
      </if>
      <if test="buildType != null" >
        build_type = #{buildType,jdbcType=INTEGER},
      </if>
      <if test="identityType != null" >
        identity_type = #{identityType,jdbcType=INTEGER},
      </if>
      <if test="identityCode != null" >
        identity_code = #{identityCode,jdbcType=VARCHAR},
      </if>
      <if test="idStartTime != null" >
        id_start_time = #{idStartTime,jdbcType=INTEGER},
      </if>
      <if test="idEndTime != null" >
        id_end_time = #{idEndTime,jdbcType=INTEGER},
      </if>
      <if test="idImages != null" >
        id_images = #{idImages,jdbcType=INTEGER},
      </if>
      <if test="isPrincipal != null" >
        is_principal = #{isPrincipal,jdbcType=SMALLINT},
      </if>
      <if test="isJoin != null" >
        is_join = #{isJoin,jdbcType=SMALLINT},
      </if>
      <if test="decorationId != null" >
        decoration_id = #{decorationId,jdbcType=INTEGER},
      </if>
      <if test="createBy != null" >
        create_by = #{createBy,jdbcType=INTEGER},
      </if>
      <if test="createTime != null" >
        create_time = #{createTime,jdbcType=INTEGER},
      </if>
      <if test="updateTime != null" >
        update_time = #{updateTime,jdbcType=INTEGER},
      </if>
    </set>
    where builder_id = #{builderId,jdbcType=INTEGER}
  </update>
  <update id="updateByPrimaryKey" parameterType="com.example.demo.model.WaysBuilder" >
    <!--
      WARNING - @mbggenerated
      This element is automatically generated by MyBatis Generator, do not modify.
      This element was generated on Tue Apr 14 15:47:07 CST 2020.
    -->
    update ways_builder
    set builder_name = #{builderName,jdbcType=VARCHAR},
      mobile = #{mobile,jdbcType=VARCHAR},
      constuction_id = #{constuctionId,jdbcType=INTEGER},
      build_type = #{buildType,jdbcType=INTEGER},
      identity_type = #{identityType,jdbcType=INTEGER},
      identity_code = #{identityCode,jdbcType=VARCHAR},
      id_start_time = #{idStartTime,jdbcType=INTEGER},
      id_end_time = #{idEndTime,jdbcType=INTEGER},
      id_images = #{idImages,jdbcType=INTEGER},
      is_principal = #{isPrincipal,jdbcType=SMALLINT},
      is_join = #{isJoin,jdbcType=SMALLINT},
      decoration_id = #{decorationId,jdbcType=INTEGER},
      create_by = #{createBy,jdbcType=INTEGER},
      create_time = #{createTime,jdbcType=INTEGER},
      update_time = #{updateTime,jdbcType=INTEGER}
    where builder_id = #{builderId,jdbcType=INTEGER}
  </update>
</mapper>